tibor/__init__.py
tibor/scraping_helpers.py
tibor-1.0.1.dist-info/LICENSE
tibor-1.0.1.dist-info/METADATA
tibor-1.0.1.dist-info/WHEEL
tibor-1.0.1.dist-info/top_level.txt
tibor-1.0.1.dist-info/RECORD
